downloadplus/__init__.py
downloadplus/downloader.py
downloadplus-1.0.0.dist-info/LICENSE
downloadplus-1.0.0.dist-info/METADATA
downloadplus-1.0.0.dist-info/WHEEL
downloadplus-1.0.0.dist-info/top_level.txt
downloadplus-1.0.0.dist-info/RECORD
