Metadata-Version: 2.1
Name: downloadplus
Version: 1.0.0
Summary: A download manager that takes urls, json files as well as Notion as an input and can download files from an URL as well as via torrent.
Home-page: https://github.com/glowingkitty/downloadplus
Author: Marco
License: UNKNOWN
Platform: UNKNOWN
Classifier: Programming Language :: Python :: 3
Classifier: License :: OSI Approved :: MIT License
Classifier: Operating System :: OS Independent
Requires-Python: >=3.6
Requires-Dist: notion
